lidirl/MCLayer.py
lidirl/__init__.py
lidirl/augmentations.py
lidirl/label.py
lidirl/make-data.py
lidirl/metrics.py
lidirl/models.py
lidirl/preprocessor.py
lidirl/trainer.py
lidirl-0.0.1.dist-info/METADATA
lidirl-0.0.1.dist-info/WHEEL
lidirl-0.0.1.dist-info/entry_points.txt
lidirl-0.0.1.dist-info/top_level.txt
lidirl-0.0.1.dist-info/RECORD
